{ "compressionlevel":-1,
 "height":44,
 "infinite":false,
 "layers":[
        {
         "data":[2, 3, 4, 5, 6, 2, 3, 4, 5, 6, 2, 3, 4, 5, 6, 2, 3, 4, 5, 6, 2, 3, 4, 5, 6, 2, 3, 4, 5, 6, 2, 3, 4, 5, 6, 2, 3, 4, 5, 6, 2, 3, 4, 5,
            2, 3, 4, 5, 6, 2, 3, 4, 5, 6, 2, 3, 4, 5, 6, 2, 3, 4, 5, 6, 2, 3, 4, 5, 6, 2, 3, 4, 5, 6, 2, 3, 4, 5, 6, 2, 3, 4, 5, 6, 2, 3, 4, 5,
            2, 4, 4, 6, 6, 3, 2, 3, 6, 3, 6, 5, 2, 5, 2, 3, 3, 2, 4, 4, 3, 2, 6, 2, 2, 6, 5, 4, 4, 5, 4, 4, 5, 5, 3, 2, 3, 4, 4, 6, 5, 4, 4, 4,
            2, 4, 5, 4, 5, 2, 6, 3, 6, 5, 4, 6, 4, 2, 2, 4, 4, 5, 3, 4, 5, 2, 4, 6, 2, 5, 4, 2, 2, 2, 5, 5, 2, 2, 5, 2, 6, 4, 3, 4, 4, 6, 4, 2,
            3, 3, 3, 2, 6, 3, 2, 3, 4, 3, 5, 5, 5, 5, 3, 6, 5, 3, 5, 4, 2, 6, 4, 4, 4, 6, 5, 5, 3, 5, 4, 3, 6, 6, 4, 3, 2, 4, 4, 5, 5, 5, 5, 3,
            2, 4, 6, 5, 5, 5, 4, 4, 5, 6, 5, 4, 6, 3, 5, 2, 2, 5, 4, 5, 2, 3, 2, 6, 6, 2, 6, 3, 4, 3, 4, 3, 6, 4, 2, 3, 5, 5, 6, 3, 6, 2, 4, 2,
            3, 3, 6, 3, 5, 2, 6, 6, 4, 4, 4, 3, 5, 5, 6, 3, 5, 4, 5, 3, 5, 6, 3, 2, 4, 4, 5, 2, 3, 3, 6, 5, 6, 4, 3, 2, 3, 6, 4, 2, 6, 3, 2, 2,
            2, 3, 4, 4, 3, 5, 4, 4, 4, 4, 2, 5, 6, 6, 2, 3, 4, 6, 3, 5, 5, 6, 6, 2, 3, 4, 6, 3, 5, 5, 18, 6, 5, 5, 2, 2, 5, 2, 3, 6, 6, 6, 3, 3,
            6, 6, 2, 5, 5, 4, 3, 6, 6, 4, 4, 3, 4, 5, 4, 6, 6, 6, 2, 5, 4, 4, 5, 4, 6, 6, 6, 2, 5, 4, 18, 3, 3, 6, 3, 2, 2, 2, 5, 4, 4, 3, 4, 4,
            3, 5, 6, 5, 4, 3, 3, 2, 6, 2, 2, 5, 4, 3, 5, 6, 6, 6, 2, 3, 3, 2, 3, 5, 6, 6, 6, 2, 3, 3, 18, 3, 2, 5, 3, 4, 3, 3, 3, 4, 6, 4, 6, 3,
            3, 3, 5, 6, 5, 5, 4, 3, 6, 5, 2, 4, 2, 5, 5, 3, 4, 4, 4, 4, 2, 3, 5, 5, 3, 4, 4, 4, 4, 2, 18, 3, 6, 2, 6, 5, 6, 6, 5, 3, 5, 5, 5, 5,
            6, 5, 6, 4, 2, 5, 2, 6, 3, 3, 3, 5, 6, 2, 2, 4, 2, 4, 5, 3, 3, 3, 2, 2, 4, 2, 4, 5, 3, 3, 18, 4, 5, 3, 3, 6, 2, 4, 2, 6, 6, 4, 6, 5,
            2, 4, 3, 2, 5, 3, 3, 3, 2, 4, 5, 6, 2, 4, 5, 6, 6, 5, 5, 4, 2, 3, 4, 5, 6, 6, 5, 5, 4, 2, 18, 2, 3, 5, 5, 5, 5, 5, 6, 4, 3, 4, 6, 3,
            2, 2, 2, 2, 2, 6, 3, 2, 4, 2, 4, 6, 4, 5, 4, 4, 5, 5, 4, 4, 4, 2, 4, 6, 2, 2, 6, 4, 6, 6, 18, 6, 6, 6, 2, 5, 2, 4, 2, 6, 4, 5, 5, 2,
            6, 6, 2, 6, 5, 2, 6, 6, 2, 6, 4, 6, 6, 4, 6, 5, 5, 5, 4, 4, 5, 5, 6, 4, 2, 5, 4, 3, 3, 6, 18, 5, 2, 6, 4, 3, 3, 6, 6, 2, 6, 4, 5, 2,
            3, 3, 4, 6, 3, 4, 5, 6, 4, 2, 6, 3, 6, 4, 2, 3, 2, 5, 5, 6, 5, 6, 2, 5, 2, 4, 2, 4, 2, 5, 18, 3, 2, 5, 3, 4, 2, 2, 4, 2, 2, 3, 4, 5,
            5, 2, 5, 6, 3, 2, 3, 3, 2, 5, 6, 6, 3, 2, 4, 5, 4, 3, 3, 6, 6, 3, 6, 4, 6, 2, 4, 6, 3, 2, 18, 2, 4, 6, 2, 3, 4, 6, 3, 5, 2, 4, 5, 6,
            2, 6, 4, 5, 2, 4, 2, 6, 3, 6, 5, 2, 5, 4, 5, 3, 3, 5, 6, 5, 5, 4, 6, 5, 3, 4, 3, 5, 6, 4, 18, 5, 2, 4, 4, 5, 5, 3, 5, 5, 5, 3, 5, 6,
            3, 2, 2, 4, 2, 2, 6, 4, 2, 4, 3, 3, 2, 2, 3, 6, 3, 2, 4, 6, 5, 6, 3, 2, 3, 2, 4, 3, 2, 5, 18, 5, 3, 6, 3, 4, 5, 4, 3, 3, 2, 3, 4, 2,
            5, 5, 5, 6, 5, 6, 5, 3, 5, 5, 6, 2, 2, 3, 6, 5, 3, 6, 6, 4, 6, 2, 5, 5, 6, 2, 5, 5, 4, 3, 4, 4, 2, 3, 6, 4, 2, 5, 2, 2, 6, 5, 2, 2,
            3, 5, 5, 4, 3, 3, 2, 6, 4, 2, 4, 6, 6, 2, 4, 3, 4, 5, 2, 4, 5, 2, 2, 4, 3, 6, 2, 5, 5, 5, 3, 4, 5, 4, 3, 5, 3, 2, 5, 5, 3, 5, 3, 3,
            3, 5, 4, 5, 2, 3, 3, 6, 6, 5, 2, 5, 6, 6, 2, 6, 5, 4, 5, 3, 2, 3, 4, 2, 5, 5, 3, 6, 2, 3, 2, 2, 6, 3, 6, 5, 5, 6, 6, 5, 4, 5, 3, 3,
            5, 5, 3, 4, 6, 4, 5, 4, 2, 3, 3, 4, 6, 3, 2, 5, 6, 6, 6, 6, 4, 2, 5, 4, 6, 2, 5, 6, 6, 3, 4, 6, 3, 6, 6, 5, 3, 3, 4, 4, 4, 3, 4, 6,
            3, 3, 3, 4, 3, 6, 2, 2, 4, 5, 2, 2, 3, 3, 5, 5, 6, 2, 6, 3, 5, 4, 5, 6, 6, 2, 4, 6, 5, 4, 2, 3, 4, 6, 5, 6, 2, 5, 4, 6, 4, 3, 5, 2,
            6, 5, 6, 5, 2, 5, 6, 3, 2, 2, 3, 2, 3, 5, 4, 3, 3, 5, 3, 2, 4, 2, 3, 6, 2, 5, 2, 6, 6, 6, 4, 4, 3, 6, 3, 2, 4, 6, 3, 4, 6, 5, 6, 5,
            5, 2, 4, 3, 6, 6, 2, 2, 4, 2, 3, 2, 3, 6, 2, 3, 2, 5, 6, 6, 3, 3, 2, 4, 3, 4, 6, 3, 5, 6, 3, 3, 3, 5, 6, 4, 2, 3, 5, 3, 3, 3, 4, 4,
            4, 6, 2, 4, 5, 2, 5, 6, 6, 4, 2, 6, 5, 2, 4, 6, 5, 4, 3, 4, 3, 6, 2, 3, 6, 2, 3, 6, 3, 2, 3, 6, 2, 4, 3, 3, 5, 3, 3, 2, 6, 5, 2, 6,
            6, 3, 5, 2, 2, 6, 5, 3, 3, 5, 2, 2, 2, 5, 4, 4, 6, 3, 6, 2, 2, 2, 4, 5, 6, 2, 5, 4, 4, 4, 3, 2, 4, 2, 6, 4, 3, 2, 4, 3, 5, 2, 5, 5,
            2, 6, 3, 5, 5, 4, 3, 5, 6, 3, 5, 5, 4, 2, 3, 2, 2, 3, 2, 4, 3, 6, 2, 6, 2, 6, 6, 5, 4, 6, 4, 5, 5, 3, 5, 2, 5, 3, 5, 3, 2, 2, 6, 6,
            2, 4, 6, 3, 5, 4, 2, 3, 5, 2, 2, 4, 3, 2, 3, 3, 2, 5, 4, 5, 5, 6, 2, 2, 4, 5, 5, 3, 4, 5, 4, 3, 5, 5, 5, 2, 6, 2, 6, 4, 5, 2, 6, 6,
            4, 5, 3, 4, 2, 6, 4, 2, 5, 4, 6, 2, 3, 3, 4, 2, 2, 3, 3, 4, 4, 5, 2, 2, 3, 2, 3, 2, 3, 4, 5, 4, 3, 6, 3, 2, 6, 5, 5, 4, 5, 4, 3, 2,
            6, 6, 3, 3, 6, 4, 2, 2, 5, 3, 3, 5, 2, 2, 6, 4, 4, 2, 3, 2, 4, 4, 4, 5, 4, 4, 5, 2, 3, 4, 6, 4, 3, 6, 5, 5, 3, 4, 2, 5, 5, 4, 5, 2,
            2, 6, 4, 4, 5, 2, 3, 2, 3, 4, 2, 6, 6, 4, 5, 6, 2, 5, 3, 2, 6, 3, 6, 6, 6, 2, 6, 3, 6, 5, 5, 4, 2, 5, 5, 6, 6, 3, 4, 4, 6, 6, 6, 3,
            0, 0, 0, 0, 0, 0, 0, 0, 0, 0, 0, 0, 0, 0, 0, 0, 0, 0, 0, 0, 0, 0, 0, 0, 0, 0, 0, 0, 0, 0, 0, 0, 0, 0, 0, 0, 0, 0, 0, 0, 0, 0, 0, 0,
            0, 0, 0, 0, 0, 0, 0, 0, 0, 0, 0, 0, 0, 0, 0, 0, 0, 0, 0, 0, 0, 0, 0, 0, 0, 0, 0, 0, 0, 0, 0, 0, 0, 0, 0, 0, 0, 0, 0, 0, 0, 0, 0, 0,
            0, 0, 0, 0, 0, 0, 0, 0, 0, 0, 0, 0, 0, 0, 0, 0, 0, 0, 0, 0, 0, 0, 0, 0, 0, 0, 0, 0, 0, 0, 0, 0, 0, 0, 0, 0, 0, 0, 0, 0, 0, 0, 0, 0,
            0, 0, 0, 0, 0, 0, 0, 0, 0, 0, 0, 0, 0, 0, 0, 0, 0, 0, 0, 0, 0, 0, 0, 0, 0, 0, 0, 0, 0, 0, 0, 0, 0, 0, 0, 0, 0, 0, 0, 0, 0, 0, 0, 0,
            0, 0, 0, 0, 0, 0, 0, 0, 0, 0, 0, 0, 0, 0, 0, 0, 0, 0, 0, 0, 0, 0, 0, 0, 0, 0, 0, 0, 0, 0, 0, 0, 0, 0, 0, 0, 0, 0, 0, 0, 0, 0, 0, 0,
            0, 0, 0, 0, 0, 0, 0, 0, 0, 0, 0, 0, 0, 0, 0, 0, 0, 0, 0, 0, 0, 0, 0, 0, 0, 0, 0, 0, 0, 0, 0, 0, 0, 0, 0, 0, 0, 0, 0, 0, 0, 0, 0, 0,
            0, 0, 0, 0, 0, 0, 0, 0, 0, 0, 0, 0, 0, 0, 0, 0, 0, 0, 0, 0, 0, 0, 0, 0, 0, 0, 0, 0, 0, 0, 0, 0, 0, 0, 0, 0, 0, 0, 0, 0, 0, 0, 0, 0,
            0, 0, 0, 0, 0, 0, 0, 0, 0, 0, 0, 0, 0, 0, 0, 0, 0, 0, 0, 0, 0, 0, 0, 0, 0, 0, 0, 0, 0, 0, 0, 0, 0, 0, 0, 0, 0, 0, 0, 0, 0, 0, 0, 0,
            0, 0, 0, 0, 0, 0, 0, 0, 0, 0, 0, 0, 0, 0, 0, 0, 0, 0, 0, 0, 0, 0, 0, 0, 0, 0, 0, 0, 0, 0, 0, 0, 0, 0, 0, 0, 0, 0, 0, 0, 0, 0, 0, 0,
            0, 0, 0, 0, 0, 0, 0, 0, 0, 0, 0, 0, 0, 0, 0, 0, 0, 0, 0, 0, 0, 0, 0, 0, 0, 0, 0, 0, 0, 0, 0, 0, 0, 0, 0, 0, 0, 0, 0, 0, 0, 0, 0, 0,
            0, 0, 0, 0, 0, 0, 0, 0, 0, 0, 0, 0, 0, 0, 0, 0, 0, 0, 0, 0, 0, 0, 0, 0, 0, 0, 0, 0, 0, 0, 0, 0, 0, 0, 0, 0, 0, 0, 0, 0, 0, 0, 0, 0],
         "height":44,
         "id":1,
         "name":"0",
         "opacity":1,
         "type":"tilelayer",
         "visible":false,
         "width":44,
         "x":0,
         "y":0
        }, 
        {
         "data":[0, 0, 0, 0, 0, 0, 0, 0, 0, 0, 0, 0, 0, 0, 0, 0, 0, 0, 0, 0, 0, 0, 0, 0, 0, 0, 0, 0, 0, 0, 0, 0, 0, 0, 0, 0, 0, 0, 0, 0, 0, 0, 0, 0,
            0, 0, 0, 0, 0, 0, 0, 0, 0, 0, 0, 0, 0, 0, 0, 0, 0, 0, 0, 0, 0, 0, 0, 0, 0, 0, 0, 0, 0, 0, 0, 0, 0, 0, 0, 0, 0, 0, 0, 0, 0, 0, 0, 0,
            0, 0, 0, 0, 0, 0, 0, 0, 0, 0, 0, 0, 0, 0, 0, 0, 0, 0, 0, 0, 0, 0, 0, 0, 0, 0, 0, 0, 0, 0, 0, 0, 0, 0, 0, 0, 0, 0, 0, 0, 0, 0, 0, 0,
            0, 0, 0, 0, 0, 0, 0, 0, 0, 0, 0, 0, 0, 0, 0, 0, 0, 0, 0, 0, 0, 0, 0, 0, 0, 0, 0, 0, 0, 0, 0, 0, 0, 0, 0, 0, 0, 0, 0, 0, 0, 0, 0, 0,
            0, 0, 0, 0, 0, 0, 0, 0, 0, 0, 0, 0, 0, 0, 0, 0, 0, 0, 0, 0, 0, 0, 0, 0, 0, 0, 0, 0, 0, 0, 0, 0, 0, 0, 0, 0, 0, 0, 0, 0, 0, 0, 0, 0,
            0, 0, 0, 0, 0, 0, 0, 0, 0, 0, 0, 0, 12, 10, 10, 10, 10, 10, 10, 10, 10, 10, 0, 0, 10, 10, 10, 10, 10, 10, 10, 13, 0, 0, 0, 0, 0, 0, 0, 0, 0, 0, 0, 0,
            0, 0, 0, 0, 0, 0, 0, 0, 0, 0, 0, 0, 20, 18, 18, 18, 18, 18, 18, 18, 18, 18, 18, 18, 18, 18, 18, 18, 18, 18, 18, 21, 0, 0, 0, 0, 0, 0, 0, 0, 0, 0, 0, 0,
            0, 0, 0, 0, 0, 0, 0, 0, 0, 0, 0, 0, 20, 18, 18, 18, 18, 18, 18, 18, 18, 18, 18, 18, 18, 18, 18, 18, 18, 18, 0, 21, 0, 0, 0, 0, 0, 0, 0, 0, 0, 0, 0, 0,
            0, 0, 0, 0, 0, 0, 0, 0, 0, 0, 0, 0, 20, 30, 26, 18, 18, 18, 18, 18, 15, 18, 30, 26, 18, 18, 18, 18, 18, 15, 0, 21, 0, 0, 0, 0, 0, 0, 0, 0, 0, 0, 0, 0,
            0, 0, 0, 0, 0, 0, 0, 0, 0, 0, 0, 0, 20, 21, 6, 18, 18, 18, 18, 3, 17, 18, 21, 3, 18, 18, 18, 18, 3, 17, 0, 21, 0, 0, 0, 0, 0, 0, 0, 0, 0, 0, 0, 0,
            0, 0, 0, 0, 0, 0, 0, 0, 0, 0, 0, 0, 20, 21, 3, 3, 18, 18, 18, 3, 17, 18, 21, 6, 3, 18, 18, 18, 3, 17, 0, 21, 0, 0, 0, 0, 0, 0, 0, 0, 0, 0, 0, 0,
            0, 0, 0, 0, 0, 0, 0, 0, 0, 0, 0, 0, 20, 21, 6, 3, 18, 18, 18, 3, 17, 18, 21, 6, 3, 18, 18, 18, 3, 17, 0, 21, 0, 0, 0, 0, 0, 0, 0, 0, 0, 0, 0, 0,
            0, 0, 0, 0, 0, 0, 0, 0, 0, 0, 0, 0, 20, 38, 10, 23, 18, 22, 10, 10, 23, 18, 38, 10, 23, 18, 22, 10, 10, 23, 0, 21, 0, 0, 0, 0, 0, 0, 0, 0, 0, 0, 0, 0,
            0, 0, 0, 0, 0, 0, 0, 0, 0, 0, 0, 0, 20, 18, 18, 18, 18, 18, 18, 18, 18, 18, 18, 18, 18, 18, 18, 18, 18, 18, 0, 21, 0, 0, 0, 0, 0, 0, 0, 0, 0, 0, 0, 0,
            0, 0, 0, 0, 0, 0, 0, 0, 0, 0, 0, 0, 20, 18, 18, 18, 18, 18, 18, 18, 18, 14, 18, 18, 18, 18, 18, 18, 18, 18, 31, 21, 0, 0, 0, 0, 0, 0, 0, 0, 0, 0, 0, 0,
            0, 0, 0, 0, 0, 0, 0, 0, 0, 0, 0, 0, 20, 18, 14, 26, 26, 26, 26, 15, 18, 19, 18, 18, 18, 18, 18, 18, 18, 18, 20, 21, 0, 0, 0, 0, 0, 0, 0, 0, 0, 0, 0, 0,
            0, 0, 0, 0, 0, 0, 0, 0, 0, 0, 0, 0, 20, 18, 19, 957, 957, 957, 3, 17, 18, 19, 18, 18, 18, 18, 18, 18, 18, 18, 20, 21, 0, 0, 0, 0, 0, 0, 0, 0, 0, 0, 0, 0,
            0, 0, 0, 0, 0, 0, 0, 0, 0, 0, 0, 0, 20, 18, 19, 957, 957, 957, 4, 17, 18, 19, 18, 18, 18, 18, 18, 18, 18, 18, 20, 21, 0, 0, 0, 0, 0, 0, 0, 0, 0, 0, 0, 0,
            0, 0, 0, 0, 0, 0, 0, 0, 0, 0, 0, 0, 20, 18, 19, 954, 3, 3, 5, 17, 18, 22, 10, 10, 23, 18, 22, 10, 10, 10, 39, 21, 0, 0, 0, 0, 0, 0, 0, 0, 0, 0, 0, 0,
            0, 0, 0, 0, 0, 0, 0, 0, 0, 0, 0, 0, 20, 18, 22, 10, 10, 10, 10, 23, 18, 18, 18, 18, 18, 18, 18, 18, 18, 18, 18, 21, 0, 0, 0, 0, 0, 0, 0, 0, 0, 0, 0, 0,
            0, 0, 0, 0, 0, 0, 0, 0, 0, 0, 0, 0, 20, 18, 18, 18, 18, 18, 18, 18, 18, 18, 14, 26, 26, 26, 26, 26, 26, 15, 18, 21, 0, 0, 0, 0, 0, 0, 0, 0, 0, 0, 0, 0,
            0, 0, 0, 0, 0, 0, 0, 0, 0, 0, 0, 0, 20, 18, 18, 18, 18, 18, 18, 18, 18, 18, 36, 34, 34, 34, 34, 34, 34, 37, 18, 21, 0, 0, 0, 0, 0, 0, 0, 0, 0, 0, 0, 0,
            0, 0, 0, 0, 0, 0, 0, 0, 0, 0, 0, 0, 20, 18, 18, 18, 18, 18, 18, 18, 18, 18, 18, 18, 18, 18, 18, 18, 18, 18, 18, 21, 0, 0, 0, 0, 0, 0, 0, 0, 0, 0, 0, 0,
            0, 0, 0, 0, 0, 0, 0, 0, 0, 0, 0, 0, 20, 18, 18, 18, 18, 18, 18, 18, 18, 18, 18, 18, 18, 18, 18, 18, 18, 18, 18, 21, 0, 0, 0, 0, 0, 0, 0, 0, 0, 0, 0, 0,
            0, 0, 0, 0, 0, 0, 0, 0, 0, 0, 0, 0, 20, 18, 18, 18, 18, 705, 706, 707, 18, 18, 18, 18, 18, 18, 18, 18, 18, 18, 18, 21, 0, 0, 0, 0, 0, 0, 0, 0, 0, 0, 0, 0,
            0, 0, 0, 0, 0, 0, 0, 0, 0, 0, 0, 0, 28, 26, 26, 26, 26, 713, 714, 715, 0, 0, 0, 0, 0, 0, 0, 0, 0, 0, 0, 4, 0, 0, 0, 0, 0, 0, 0, 0, 0, 0, 0, 0,
            0, 0, 0, 0, 0, 0, 0, 0, 0, 0, 0, 0, 6, 0, 0, 0, 0, 713, 714, 715, 0, 0, 0, 0, 0, 0, 0, 0, 0, 0, 0, 6, 0, 0, 0, 0, 0, 0, 0, 0, 0, 0, 0, 0,
            0, 0, 0, 0, 0, 0, 0, 0, 0, 0, 0, 0, 4, 0, 0, 0, 0, 713, 714, 715, 0, 0, 0, 0, 0, 0, 0, 0, 0, 0, 0, 3, 0, 0, 0, 0, 0, 0, 0, 0, 0, 0, 0, 0,
            0, 0, 0, 0, 0, 0, 0, 0, 0, 0, 0, 0, 3, 0, 0, 0, 0, 713, 714, 715, 0, 0, 0, 0, 0, 0, 0, 0, 0, 0, 0, 5, 0, 0, 0, 0, 0, 0, 0, 0, 0, 0, 0, 0,
            0, 0, 0, 0, 0, 0, 0, 0, 0, 0, 0, 0, 6, 0, 0, 0, 0, 713, 714, 715, 0, 0, 0, 0, 0, 0, 0, 0, 0, 0, 0, 4, 0, 0, 0, 0, 0, 0, 0, 0, 0, 0, 0, 0,
            0, 0, 0, 0, 0, 0, 0, 0, 0, 0, 0, 0, 6, 0, 0, 0, 0, 713, 714, 715, 0, 0, 0, 0, 0, 0, 0, 0, 0, 0, 0, 6, 0, 0, 0, 0, 0, 0, 0, 0, 0, 0, 0, 0,
            0, 0, 0, 0, 0, 0, 0, 0, 0, 0, 0, 0, 6, 0, 0, 0, 0, 713, 714, 715, 0, 0, 0, 0, 0, 0, 0, 0, 0, 0, 0, 4, 0, 0, 0, 0, 0, 0, 0, 0, 0, 0, 0, 0,
            0, 0, 0, 0, 0, 0, 0, 0, 0, 0, 0, 0, 0, 0, 0, 0, 0, 713, 714, 715, 0, 0, 0, 0, 0, 0, 0, 0, 0, 0, 0, 0, 0, 0, 0, 0, 0, 0, 0, 0, 0, 0, 0, 0,
            0, 0, 0, 0, 0, 0, 0, 0, 0, 0, 0, 0, 0, 0, 0, 0, 0, 0, 0, 0, 0, 0, 0, 0, 0, 0, 0, 0, 0, 0, 0, 0, 0, 0, 0, 0, 0, 0, 0, 0, 0, 0, 0, 0,
            0, 0, 0, 0, 0, 0, 0, 0, 0, 0, 0, 0, 0, 0, 0, 0, 0, 0, 0, 0, 0, 0, 0, 0, 0, 0, 0, 0, 0, 0, 0, 0, 0, 0, 0, 0, 0, 0, 0, 0, 0, 0, 0, 0,
            0, 0, 0, 0, 0, 0, 0, 0, 0, 0, 0, 0, 0, 0, 0, 0, 0, 0, 0, 0, 0, 0, 0, 0, 0, 0, 0, 0, 0, 0, 0, 0, 0, 0, 0, 0, 0, 0, 0, 0, 0, 0, 0, 0,
            0, 0, 0, 0, 0, 0, 0, 0, 0, 0, 0, 0, 0, 0, 0, 0, 0, 0, 0, 0, 0, 0, 0, 0, 0, 0, 0, 0, 0, 0, 0, 0, 0, 0, 0, 0, 0, 0, 0, 0, 0, 0, 0, 0,
            0, 0, 0, 0, 0, 0, 0, 0, 0, 0, 0, 0, 0, 0, 0, 0, 0, 0, 0, 0, 0, 0, 0, 0, 0, 0, 0, 0, 0, 0, 0, 0, 0, 0, 0, 0, 0, 0, 0, 0, 0, 0, 0, 0,
            0, 0, 0, 0, 0, 0, 0, 0, 0, 0, 0, 0, 0, 0, 0, 0, 0, 0, 0, 0, 0, 0, 0, 0, 0, 0, 0, 0, 0, 0, 0, 0, 0, 0, 0, 0, 0, 0, 0, 0, 0, 0, 0, 0,
            0, 0, 0, 0, 0, 0, 0, 0, 0, 0, 0, 0, 0, 0, 0, 0, 0, 0, 0, 0, 0, 0, 0, 0, 0, 0, 0, 0, 0, 0, 0, 0, 0, 0, 0, 0, 0, 0, 0, 0, 0, 0, 0, 0,
            0, 0, 0, 0, 0, 0, 0, 0, 0, 0, 0, 0, 0, 0, 0, 0, 0, 0, 0, 0, 0, 0, 0, 0, 0, 0, 0, 0, 0, 0, 0, 0, 0, 0, 0, 0, 0, 0, 0, 0, 0, 0, 0, 0,
            0, 0, 0, 0, 0, 0, 0, 0, 0, 0, 0, 0, 0, 0, 0, 0, 0, 0, 0, 0, 0, 0, 0, 0, 0, 0, 0, 0, 0, 0, 0, 0, 0, 0, 0, 0, 0, 0, 0, 0, 0, 0, 0, 0,
            0, 0, 0, 0, 0, 0, 0, 0, 0, 0, 0, 0, 0, 0, 0, 0, 0, 0, 0, 0, 0, 0, 0, 0, 0, 0, 0, 0, 0, 0, 0, 0, 0, 0, 0, 0, 0, 0, 0, 0, 0, 0, 0, 0,
            0, 0, 0, 0, 0, 0, 0, 0, 0, 0, 0, 0, 0, 0, 0, 0, 0, 0, 0, 0, 0, 0, 0, 0, 0, 0, 0, 0, 0, 0, 0, 0, 0, 0, 0, 0, 0, 0, 0, 0, 0, 0, 0, 0],
         "height":44,
         "id":3,
         "name":"1",
         "opacity":1,
         "type":"tilelayer",
         "visible":false,
         "width":44,
         "x":0,
         "y":0
        }, 
        {
         "data":[417, 418, 417, 418, 419, 420, 417, 418, 419, 420, 417, 418, 419, 420, 417, 418, 419, 420, 417, 418, 419, 420, 7, 7, 417, 418, 419, 420, 417, 418, 419, 420, 417, 418, 419, 420, 417, 418, 419, 420, 417, 418, 419, 420,
            425, 426, 425, 426, 427, 428, 425, 426, 427, 428, 425, 426, 427, 428, 425, 426, 427, 428, 425, 426, 427, 428, 7, 7, 425, 426, 427, 428, 425, 426, 427, 428, 425, 426, 427, 428, 425, 426, 427, 428, 425, 426, 427, 428,
            417, 418, 419, 420, 417, 418, 419, 420, 417, 418, 419, 420, 417, 418, 419, 420, 417, 418, 419, 420, 419, 420, 7, 7, 417, 418, 419, 420, 417, 418, 419, 420, 417, 418, 419, 420, 417, 418, 419, 420, 417, 418, 419, 420,
            425, 426, 427, 428, 425, 426, 427, 428, 425, 426, 427, 428, 425, 426, 427, 428, 425, 426, 427, 428, 427, 428, 12, 13, 425, 426, 427, 428, 425, 426, 427, 428, 425, 426, 427, 428, 425, 426, 427, 428, 425, 426, 427, 428,
            417, 418, 419, 420, 417, 418, 419, 420, 417, 418, 419, 420, 433, 434, 435, 436, 433, 434, 435, 436, 435, 436, 20, 21, 433, 434, 435, 436, 433, 434, 435, 436, 417, 418, 419, 420, 417, 418, 419, 420, 417, 418, 419, 420,
            425, 426, 427, 428, 425, 426, 427, 428, 425, 426, 427, 428, 0, 0, 0, 0, 0, 0, 0, 0, 0, 10, 39, 38, 10, 0, 0, 0, 0, 0, 0, 0, 425, 426, 427, 428, 425, 426, 427, 428, 425, 426, 427, 428,
            417, 418, 419, 420, 417, 418, 419, 420, 417, 418, 419, 420, 0, 0, 0, 0, 0, 0, 0, 0, 0, 0, 0, 0, 0, 0, 0, 0, 0, 0, 0, 0, 417, 418, 419, 420, 417, 418, 419, 420, 417, 418, 419, 420,
            425, 426, 427, 428, 425, 426, 427, 428, 425, 426, 427, 428, 0, 0, 0, 1577, 1578, 1579, 1580, 1581, 0, 0, 0, 0, 1577, 1578, 1579, 1580, 1581, 0, 0, 0, 425, 426, 427, 428, 425, 426, 427, 428, 425, 426, 427, 428,
            417, 418, 419, 420, 417, 418, 419, 420, 417, 418, 419, 420, 0, 0, 0, 1585, 1586, 1587, 1588, 1589, 0, 0, 0, 0, 1585, 1586, 1587, 1588, 1589, 0, 0, 0, 417, 418, 419, 420, 417, 418, 419, 420, 417, 418, 419, 420,
            425, 426, 427, 428, 425, 426, 427, 428, 425, 426, 427, 428, 0, 0, 0, 1593, 1594, 1595, 1596, 1597, 0, 0, 0, 0, 1593, 1594, 1595, 1596, 1597, 0, 0, 0, 425, 426, 427, 428, 425, 426, 427, 428, 425, 426, 427, 428,
            417, 418, 419, 420, 417, 418, 419, 420, 417, 418, 419, 420, 0, 0, 963, 1601, 1602, 1603, 1604, 1605, 0, 0, 0, 963, 1601, 1602, 1603, 1604, 1605, 0, 0, 0, 417, 418, 419, 420, 417, 418, 419, 420, 417, 418, 419, 420,
            425, 426, 427, 428, 425, 426, 427, 428, 425, 426, 427, 428, 0, 0, 971, 1609, 1610, 1611, 1612, 1613, 0, 0, 0, 971, 1609, 1610, 1611, 1612, 1613, 0, 0, 0, 425, 426, 427, 428, 425, 426, 427, 428, 425, 426, 427, 428,
            417, 418, 419, 420, 417, 418, 419, 420, 417, 418, 419, 420, 0, 0, 0, 0, 0, 0, 0, 0, 0, 0, 0, 0, 0, 0, 0, 0, 0, 0, 0, 0, 417, 418, 419, 420, 417, 418, 419, 420, 417, 418, 419, 420,
            425, 426, 427, 428, 425, 426, 427, 428, 425, 426, 427, 428, 0, 0, 0, 0, 0, 0, 0, 0, 0, 0, 3089, 3090, 3091, 3092, 3093, 3094, 3095, 3096, 0, 0, 425, 426, 427, 428, 425, 426, 427, 428, 425, 426, 427, 428,
            417, 418, 419, 420, 417, 418, 419, 420, 417, 418, 419, 420, 0, 0, 0, 0, 0, 0, 0, 0, 0, 0, 3097, 3098, 3099, 3100, 3101, 3102, 3103, 3104, 0, 0, 417, 418, 419, 420, 417, 418, 419, 420, 417, 418, 419, 420,
            425, 426, 427, 428, 425, 426, 427, 428, 425, 426, 427, 428, 0, 0, 0, 1297, 1298, 1299, 953, 0, 0, 0, 3105, 3106, 3107, 3108, 3109, 3110, 3111, 3112, 0, 0, 425, 426, 427, 428, 425, 426, 427, 428, 425, 426, 427, 428,
            417, 418, 419, 420, 417, 418, 419, 420, 417, 418, 419, 420, 0, 0, 0, 0, 0, 0, 0, 0, 0, 0, 3113, 3114, 3115, 3116, 3117, 3118, 3119, 3120, 0, 0, 417, 418, 419, 420, 417, 418, 419, 420, 417, 418, 419, 420,
            425, 426, 427, 428, 425, 426, 427, 428, 425, 426, 427, 428, 0, 0, 0, 0, 0, 0, 0, 0, 0, 0, 3121, 3122, 3123, 3124, 3125, 3126, 3127, 3128, 0, 0, 425, 426, 427, 428, 425, 426, 427, 428, 425, 426, 427, 428,
            417, 418, 419, 420, 417, 418, 419, 420, 417, 418, 419, 420, 0, 0, 0, 0, 0, 0, 0, 0, 0, 0, 0, 0, 0, 0, 0, 0, 0, 0, 0, 0, 417, 418, 419, 420, 417, 418, 419, 420, 417, 418, 419, 420,
            425, 426, 427, 428, 425, 426, 427, 428, 425, 426, 427, 428, 0, 0, 0, 0, 0, 0, 0, 0, 0, 0, 0, 0, 0, 0, 0, 0, 0, 0, 0, 0, 425, 426, 427, 428, 425, 426, 427, 428, 425, 426, 427, 428,
            417, 418, 419, 420, 417, 418, 419, 420, 417, 418, 419, 420, 0, 0, 0, 0, 0, 0, 0, 0, 0, 0, 0, 0, 0, 0, 0, 0, 0, 0, 0, 0, 417, 418, 419, 420, 417, 418, 419, 420, 417, 418, 419, 420,
            425, 426, 427, 428, 425, 426, 427, 428, 425, 426, 427, 428, 0, 0, 0, 0, 0, 0, 0, 0, 0, 0, 0, 1297, 1298, 1298, 1298, 953, 1299, 0, 0, 0, 425, 426, 427, 428, 425, 426, 427, 428, 425, 426, 427, 428,
            417, 418, 419, 420, 417, 418, 419, 420, 417, 418, 419, 420, 0, 0, 0, 0, 0, 0, 0, 0, 0, 0, 0, 0, 0, 0, 0, 0, 0, 0, 0, 0, 417, 418, 419, 420, 417, 418, 419, 420, 417, 418, 419, 420,
            425, 426, 427, 428, 425, 426, 427, 428, 425, 426, 427, 428, 0, 0, 0, 0, 705, 706, 706, 707, 0, 0, 0, 0, 0, 0, 0, 0, 0, 0, 0, 0, 425, 426, 427, 428, 425, 426, 427, 428, 425, 426, 427, 428,
            417, 418, 419, 420, 417, 418, 419, 420, 417, 418, 419, 420, 421, 422, 421, 422, 713, 714, 714, 715, 26, 26, 26, 26, 26, 26, 26, 26, 26, 26, 26, 29, 417, 418, 419, 420, 417, 418, 419, 420, 417, 418, 419, 420,
            425, 426, 427, 428, 425, 426, 427, 428, 425, 426, 427, 428, 429, 430, 429, 430, 713, 714, 0, 0, 0, 0, 0, 0, 0, 0, 0, 0, 0, 0, 0, 0, 425, 426, 427, 428, 425, 426, 427, 428, 425, 426, 427, 428,
            417, 418, 419, 420, 417, 418, 419, 420, 417, 418, 419, 420, 417, 418, 419, 420, 713, 714, 0, 0, 421, 422, 421, 422, 421, 422, 421, 422, 421, 422, 421, 422, 417, 418, 419, 420, 417, 418, 419, 420, 417, 418, 419, 420,
            425, 426, 427, 428, 425, 426, 427, 428, 425, 426, 427, 428, 425, 426, 427, 428, 713, 714, 0, 0, 429, 430, 429, 430, 429, 430, 429, 430, 429, 430, 429, 430, 425, 426, 427, 428, 425, 426, 427, 428, 425, 426, 427, 428,
            417, 418, 419, 420, 417, 418, 419, 420, 417, 418, 419, 420, 417, 418, 419, 420, 713, 714, 0, 0, 417, 418, 419, 420, 417, 418, 419, 420, 417, 418, 419, 420, 417, 418, 419, 420, 417, 418, 419, 420, 417, 418, 419, 420,
            425, 426, 427, 428, 425, 426, 427, 428, 425, 426, 427, 428, 425, 426, 427, 428, 713, 714, 0, 0, 425, 426, 427, 428, 425, 426, 427, 428, 425, 426, 427, 428, 425, 426, 427, 428, 425, 426, 427, 428, 425, 426, 427, 428,
            417, 418, 419, 420, 417, 418, 419, 420, 417, 418, 419, 420, 417, 418, 419, 420, 713, 714, 0, 0, 417, 418, 419, 420, 417, 418, 419, 420, 417, 418, 419, 420, 417, 418, 419, 420, 417, 418, 419, 420, 417, 418, 419, 420,
            425, 426, 427, 428, 425, 426, 427, 428, 425, 426, 427, 428, 425, 426, 427, 428, 713, 714, 0, 0, 425, 426, 427, 428, 425, 426, 427, 428, 425, 426, 427, 428, 425, 426, 427, 428, 425, 426, 427, 428, 425, 426, 427, 428,
            417, 418, 419, 420, 417, 418, 419, 420, 417, 418, 419, 420, 433, 434, 435, 436, 713, 714, 0, 0, 433, 434, 435, 436, 433, 434, 435, 436, 433, 434, 435, 436, 433, 434, 435, 436, 433, 434, 435, 436, 433, 434, 435, 436,
            0, 0, 0, 0, 0, 0, 0, 0, 0, 0, 0, 0, 0, 0, 0, 0, 0, 0, 0, 0, 0, 0, 0, 0, 0, 0, 0, 0, 0, 0, 0, 0, 0, 0, 0, 0, 0, 0, 0, 0, 0, 0, 0, 0,
            0, 0, 0, 0, 0, 0, 0, 0, 0, 0, 0, 0, 0, 0, 0, 0, 0, 0, 0, 0, 0, 0, 0, 0, 0, 0, 0, 0, 0, 0, 0, 0, 0, 0, 0, 0, 0, 0, 0, 0, 0, 0, 0, 0,
            0, 0, 0, 0, 0, 0, 0, 0, 0, 0, 0, 0, 0, 0, 0, 0, 0, 0, 0, 0, 0, 0, 0, 0, 0, 0, 0, 0, 0, 0, 0, 0, 0, 0, 0, 0, 0, 0, 0, 0, 0, 0, 0, 0,
            0, 0, 0, 0, 0, 0, 0, 0, 0, 0, 0, 0, 0, 0, 0, 0, 0, 0, 0, 0, 0, 0, 0, 0, 0, 0, 0, 0, 0, 0, 0, 0, 0, 0, 0, 0, 0, 0, 0, 0, 0, 0, 0, 0,
            0, 0, 0, 0, 0, 0, 0, 0, 0, 0, 0, 0, 0, 0, 0, 0, 0, 0, 0, 0, 0, 0, 0, 0, 0, 0, 0, 0, 0, 0, 0, 0, 0, 0, 0, 0, 0, 0, 0, 0, 0, 0, 0, 0,
            0, 0, 0, 0, 0, 0, 0, 0, 0, 0, 0, 0, 0, 0, 0, 0, 0, 0, 0, 0, 0, 0, 0, 0, 0, 0, 0, 0, 0, 0, 0, 0, 0, 0, 0, 0, 0, 0, 0, 0, 0, 0, 0, 0,
            0, 0, 0, 0, 0, 0, 0, 0, 0, 0, 0, 0, 0, 0, 0, 0, 0, 0, 0, 0, 0, 0, 0, 0, 0, 0, 0, 0, 0, 0, 0, 0, 0, 0, 0, 0, 0, 0, 0, 0, 0, 0, 0, 0,
            0, 0, 0, 0, 0, 0, 0, 0, 0, 0, 0, 0, 0, 0, 0, 0, 0, 0, 0, 0, 0, 0, 0, 0, 0, 0, 0, 0, 0, 0, 0, 0, 0, 0, 0, 0, 0, 0, 0, 0, 0, 0, 0, 0,
            0, 0, 0, 0, 0, 0, 0, 0, 0, 0, 0, 0, 0, 0, 0, 0, 0, 0, 0, 0, 0, 0, 0, 0, 0, 0, 0, 0, 0, 0, 0, 0, 0, 0, 0, 0, 0, 0, 0, 0, 0, 0, 0, 0,
            0, 0, 0, 0, 0, 0, 0, 0, 0, 0, 0, 0, 0, 0, 0, 0, 0, 0, 0, 0, 0, 0, 0, 0, 0, 0, 0, 0, 0, 0, 0, 0, 0, 0, 0, 0, 0, 0, 0, 0, 0, 0, 0, 0,
            0, 0, 0, 0, 0, 0, 0, 0, 0, 0, 0, 0, 0, 0, 0, 0, 0, 0, 0, 0, 0, 0, 0, 0, 0, 0, 0, 0, 0, 0, 0, 0, 0, 0, 0, 0, 0, 0, 0, 0, 0, 0, 0, 0],
         "height":44,
         "id":2,
         "name":"2",
         "opacity":1,
         "type":"tilelayer",
         "visible":false,
         "width":44,
         "x":0,
         "y":0
        }, 
        {
         "data":[0, 0, 0, 0, 0, 0, 0, 0, 0, 0, 0, 0, 0, 0, 0, 0, 0, 0, 0, 0, 0, 64, 0, 0, 64, 0, 0, 0, 0, 0, 0, 0, 0, 0, 0, 0, 0, 0, 0, 0, 0, 0, 0, 0,
            0, 0, 0, 0, 0, 0, 0, 0, 0, 0, 0, 0, 0, 0, 0, 0, 0, 0, 0, 0, 0, 64, 0, 0, 64, 0, 0, 0, 0, 0, 0, 0, 0, 0, 0, 0, 0, 0, 0, 0, 0, 0, 0, 0,
            0, 0, 0, 0, 0, 0, 0, 0, 0, 0, 0, 0, 0, 0, 0, 0, 0, 0, 0, 0, 0, 64, 0, 0, 64, 0, 0, 0, 0, 0, 0, 0, 0, 0, 0, 0, 0, 0, 0, 0, 0, 0, 0, 0,
            0, 0, 0, 0, 0, 0, 0, 0, 0, 0, 0, 0, 0, 0, 0, 0, 0, 0, 0, 0, 0, 64, 0, 0, 64, 0, 0, 0, 0, 0, 0, 0, 0, 0, 0, 0, 0, 0, 0, 0, 0, 0, 0, 0,
            0, 0, 0, 0, 0, 0, 0, 0, 0, 0, 0, 0, 64, 64, 64, 64, 64, 64, 64, 64, 64, 64, 0, 0, 64, 64, 64, 64, 64, 64, 64, 64, 0, 0, 0, 0, 0, 0, 0, 0, 0, 0, 0, 0,
            0, 0, 0, 0, 0, 0, 0, 0, 0, 0, 0, 64, 0, 0, 0, 0, 0, 0, 0, 0, 0, 0, 0, 0, 0, 0, 0, 0, 0, 0, 0, 0, 64, 0, 0, 0, 0, 0, 0, 0, 0, 0, 0, 0,
            0, 0, 0, 0, 0, 0, 0, 0, 0, 0, 0, 64, 0, 0, 0, 0, 0, 0, 0, 0, 0, 0, 0, 0, 0, 0, 0, 0, 0, 0, 0, 0, 64, 0, 0, 0, 0, 0, 0, 0, 0, 0, 0, 0,
            0, 0, 0, 0, 0, 0, 0, 0, 0, 0, 0, 64, 0, 0, 0, 0, 0, 0, 0, 0, 0, 0, 0, 0, 0, 0, 0, 0, 0, 0, 0, 0, 64, 0, 0, 0, 0, 0, 0, 0, 0, 0, 0, 0,
            0, 0, 0, 0, 0, 0, 0, 0, 0, 0, 0, 64, 0, 0, 0, 64, 64, 64, 64, 64, 0, 0, 0, 0, 64, 64, 64, 64, 64, 0, 0, 0, 64, 0, 0, 0, 0, 0, 0, 0, 0, 0, 0, 0,
            0, 0, 0, 0, 0, 0, 0, 0, 0, 0, 0, 64, 0, 0, 0, 64, 0, 0, 0, 64, 0, 0, 0, 0, 64, 0, 0, 0, 64, 0, 0, 0, 64, 0, 0, 0, 0, 0, 0, 0, 0, 0, 0, 0,
            0, 0, 0, 0, 0, 0, 0, 0, 0, 0, 0, 64, 0, 0, 0, 64, 64, 0, 0, 64, 0, 0, 0, 0, 64, 64, 64, 0, 64, 0, 0, 0, 64, 0, 0, 0, 0, 0, 0, 0, 0, 0, 0, 0,
            0, 0, 0, 0, 0, 0, 0, 0, 0, 0, 0, 64, 0, 0, 64, 64, 0, 64, 64, 64, 0, 0, 0, 64, 64, 0, 64, 64, 64, 0, 0, 0, 64, 0, 0, 0, 0, 0, 0, 0, 0, 0, 0, 0,
            0, 0, 0, 0, 0, 0, 0, 0, 0, 0, 0, 64, 0, 0, 0, 0, 0, 0, 0, 0, 0, 0, 0, 0, 0, 0, 0, 0, 0, 0, 0, 0, 64, 0, 0, 0, 0, 0, 0, 0, 0, 0, 0, 0,
            0, 0, 0, 0, 0, 0, 0, 0, 0, 0, 0, 64, 0, 0, 0, 0, 0, 0, 0, 0, 0, 0, 0, 0, 0, 0, 0, 0, 0, 0, 0, 0, 64, 0, 0, 0, 0, 0, 0, 0, 0, 0, 0, 0,
            0, 0, 0, 0, 0, 0, 0, 0, 0, 0, 0, 64, 0, 0, 0, 0, 0, 0, 0, 0, 0, 0, 64, 64, 64, 64, 64, 64, 64, 64, 0, 0, 64, 0, 0, 0, 0, 0, 0, 0, 0, 0, 0, 0,
            0, 0, 0, 0, 0, 0, 0, 0, 0, 0, 0, 64, 0, 0, 0, 64, 64, 64, 64, 0, 0, 0, 64, 0, 0, 0, 0, 0, 0, 64, 0, 0, 64, 0, 0, 0, 0, 0, 0, 0, 0, 0, 0, 0,
            0, 0, 0, 0, 0, 0, 0, 0, 0, 0, 0, 64, 0, 0, 0, 0, 0, 0, 0, 0, 0, 0, 64, 0, 64, 64, 64, 0, 0, 64, 0, 0, 64, 0, 0, 0, 0, 0, 0, 0, 0, 0, 0, 0,
            0, 0, 0, 0, 0, 0, 0, 0, 0, 0, 0, 64, 0, 0, 0, 0, 0, 0, 0, 0, 0, 0, 64, 64, 64, 0, 64, 64, 64, 64, 0, 0, 64, 0, 0, 0, 0, 0, 0, 0, 0, 0, 0, 0,
            0, 0, 0, 0, 0, 0, 0, 0, 0, 0, 0, 64, 0, 0, 0, 64, 0, 0, 0, 0, 0, 0, 0, 0, 0, 0, 0, 0, 0, 0, 0, 0, 64, 0, 0, 0, 0, 0, 0, 0, 0, 0, 0, 0,
            0, 0, 0, 0, 0, 0, 0, 0, 0, 0, 0, 64, 0, 0, 0, 0, 0, 0, 0, 0, 0, 0, 0, 0, 0, 0, 0, 0, 0, 0, 0, 0, 64, 0, 0, 0, 0, 0, 0, 0, 0, 0, 0, 0,
            0, 0, 0, 0, 0, 0, 0, 0, 0, 0, 0, 64, 0, 0, 0, 0, 0, 0, 0, 0, 0, 0, 0, 0, 0, 0, 0, 0, 0, 0, 0, 0, 64, 0, 0, 0, 0, 0, 0, 0, 0, 0, 0, 0,
            0, 0, 0, 0, 0, 0, 0, 0, 0, 0, 0, 64, 0, 0, 0, 0, 0, 0, 0, 0, 0, 0, 0, 64, 64, 64, 64, 64, 64, 0, 0, 0, 64, 0, 0, 0, 0, 0, 0, 0, 0, 0, 0, 0,
            0, 0, 0, 0, 0, 0, 0, 0, 0, 0, 0, 64, 0, 0, 0, 0, 0, 0, 0, 0, 0, 0, 0, 0, 0, 0, 0, 0, 0, 0, 0, 0, 64, 0, 0, 0, 0, 0, 0, 0, 0, 0, 0, 0,
            0, 0, 0, 0, 0, 0, 0, 0, 0, 0, 0, 64, 0, 0, 0, 0, 64, 64, 64, 64, 0, 0, 0, 0, 0, 0, 0, 0, 0, 0, 0, 0, 64, 0, 0, 0, 0, 0, 0, 0, 0, 0, 0, 0,
            0, 0, 0, 0, 0, 0, 0, 0, 0, 0, 0, 64, 0, 0, 0, 0, 64, 0, 0, 64, 0, 0, 0, 0, 0, 0, 0, 0, 0, 0, 0, 0, 64, 0, 0, 0, 0, 0, 0, 0, 0, 0, 0, 0,
            0, 0, 0, 0, 0, 0, 0, 0, 0, 0, 0, 0, 64, 64, 64, 64, 0, 0, 0, 64, 0, 0, 0, 0, 0, 0, 0, 0, 0, 0, 0, 0, 64, 0, 0, 0, 0, 0, 0, 0, 0, 0, 0, 0,
            0, 0, 0, 0, 0, 0, 0, 0, 0, 0, 0, 0, 0, 0, 0, 0, 0, 0, 0, 64, 0, 0, 0, 0, 0, 0, 0, 0, 0, 0, 0, 0, 64, 0, 0, 0, 0, 0, 0, 0, 0, 0, 0, 0,
            0, 0, 0, 0, 0, 0, 0, 0, 0, 0, 0, 0, 0, 0, 0, 0, 0, 0, 0, 0, 64, 64, 64, 64, 64, 64, 64, 64, 64, 64, 64, 64, 0, 0, 0, 0, 0, 0, 0, 0, 0, 0, 0, 0,
            0, 0, 0, 0, 0, 0, 0, 0, 0, 0, 0, 0, 0, 0, 0, 0, 0, 0, 0, 0, 0, 0, 0, 0, 0, 0, 0, 0, 0, 0, 0, 0, 0, 0, 0, 0, 0, 0, 0, 0, 0, 0, 0, 0,
            0, 0, 0, 0, 0, 0, 0, 0, 0, 0, 0, 0, 0, 0, 0, 0, 0, 0, 0, 0, 0, 0, 0, 0, 0, 0, 0, 0, 0, 0, 0, 0, 0, 0, 0, 0, 0, 0, 0, 0, 0, 0, 0, 0,
            0, 0, 0, 0, 0, 0, 0, 0, 0, 0, 0, 0, 0, 0, 0, 0, 0, 0, 0, 0, 0, 0, 0, 0, 0, 0, 0, 0, 0, 0, 0, 0, 0, 0, 0, 0, 0, 0, 0, 0, 0, 0, 0, 0,
            0, 0, 0, 0, 0, 0, 0, 0, 0, 0, 0, 0, 0, 0, 0, 0, 0, 0, 0, 0, 0, 0, 0, 0, 0, 0, 0, 0, 0, 0, 0, 0, 0, 0, 0, 0, 0, 0, 0, 0, 0, 0, 0, 0,
            0, 0, 0, 0, 0, 0, 0, 0, 0, 0, 0, 0, 0, 0, 0, 0, 0, 0, 0, 0, 0, 0, 0, 0, 0, 0, 0, 0, 0, 0, 0, 0, 0, 0, 0, 0, 0, 0, 0, 0, 0, 0, 0, 0,
            0, 0, 0, 0, 0, 0, 0, 0, 0, 0, 0, 0, 0, 0, 0, 0, 0, 0, 0, 0, 0, 0, 0, 0, 0, 0, 0, 0, 0, 0, 0, 0, 0, 0, 0, 0, 0, 0, 0, 0, 0, 0, 0, 0,
            0, 0, 0, 0, 0, 0, 0, 0, 0, 0, 0, 0, 0, 0, 0, 0, 0, 0, 0, 0, 0, 0, 0, 0, 0, 0, 0, 0, 0, 0, 0, 0, 0, 0, 0, 0, 0, 0, 0, 0, 0, 0, 0, 0,
            0, 0, 0, 0, 0, 0, 0, 0, 0, 0, 0, 0, 0, 0, 0, 0, 0, 0, 0, 0, 0, 0, 0, 0, 0, 0, 0, 0, 0, 0, 0, 0, 0, 0, 0, 0, 0, 0, 0, 0, 0, 0, 0, 0,
            0, 0, 0, 0, 0, 0, 0, 0, 0, 0, 0, 0, 0, 0, 0, 0, 0, 0, 0, 0, 0, 0, 0, 0, 0, 0, 0, 0, 0, 0, 0, 0, 0, 0, 0, 0, 0, 0, 0, 0, 0, 0, 0, 0,
            0, 0, 0, 0, 0, 0, 0, 0, 0, 0, 0, 0, 0, 0, 0, 0, 0, 0, 0, 0, 0, 0, 0, 0, 0, 0, 0, 0, 0, 0, 0, 0, 0, 0, 0, 0, 0, 0, 0, 0, 0, 0, 0, 0,
            0, 0, 0, 0, 0, 0, 0, 0, 0, 0, 0, 0, 0, 0, 0, 0, 0, 0, 0, 0, 0, 0, 0, 0, 0, 0, 0, 0, 0, 0, 0, 0, 0, 0, 0, 0, 0, 0, 0, 0, 0, 0, 0, 0,
            0, 0, 0, 0, 0, 0, 0, 0, 0, 0, 0, 0, 0, 0, 0, 0, 0, 0, 0, 0, 0, 0, 0, 0, 0, 0, 0, 0, 0, 0, 0, 0, 0, 0, 0, 0, 0, 0, 0, 0, 0, 0, 0, 0,
            0, 0, 0, 0, 0, 0, 0, 0, 0, 0, 0, 0, 0, 0, 0, 0, 0, 0, 0, 0, 0, 0, 0, 0, 0, 0, 0, 0, 0, 0, 0, 0, 0, 0, 0, 0, 0, 0, 0, 0, 0, 0, 0, 0,
            0, 0, 0, 0, 0, 0, 0, 0, 0, 0, 0, 0, 0, 0, 0, 0, 0, 0, 0, 0, 0, 0, 0, 0, 0, 0, 0, 0, 0, 0, 0, 0, 0, 0, 0, 0, 0, 0, 0, 0, 0, 0, 0, 0,
            0, 0, 0, 0, 0, 0, 0, 0, 0, 0, 0, 0, 0, 0, 0, 0, 0, 0, 0, 0, 0, 0, 0, 0, 0, 0, 0, 0, 0, 0, 0, 0, 0, 0, 0, 0, 0, 0, 0, 0, 0, 0, 0, 0,
            0, 0, 0, 0, 0, 0, 0, 0, 0, 0, 0, 0, 0, 0, 0, 0, 0, 0, 0, 0, 0, 0, 0, 0, 0, 0, 0, 0, 0, 0, 0, 0, 0, 0, 0, 0, 0, 0, 0, 0, 0, 0, 0, 0],
         "height":44,
         "id":4,
         "name":"4",
         "opacity":1,
         "type":"tilelayer",
         "visible":true,
         "width":44,
         "x":0,
         "y":0
        }, 
        {
         "data":[0, 0, 0, 0, 0, 0, 0, 0, 0, 0, 0, 0, 0, 0, 0, 0, 0, 0, 0, 0, 0, 0, 0, 0, 0, 0, 0, 0, 0, 0, 0, 0, 0, 0, 0, 0, 0, 0, 0, 0, 0, 0, 0, 0,
            0, 0, 0, 0, 0, 0, 0, 0, 0, 0, 0, 0, 0, 0, 0, 0, 0, 0, 0, 0, 0, 0, 0, 0, 0, 0, 0, 0, 0, 0, 0, 0, 0, 0, 0, 0, 0, 0, 0, 0, 0, 0, 0, 0,
            0, 0, 0, 0, 0, 0, 0, 0, 0, 0, 0, 0, 0, 0, 0, 0, 0, 0, 0, 0, 0, 0, 0, 0, 0, 0, 0, 0, 0, 0, 0, 0, 0, 0, 0, 0, 0, 0, 0, 0, 0, 0, 0, 0,
            0, 0, 0, 0, 0, 0, 0, 0, 0, 0, 0, 0, 0, 0, 0, 0, 0, 0, 0, 0, 0, 0, 0, 0, 0, 0, 0, 0, 0, 0, 0, 0, 0, 0, 0, 0, 0, 0, 0, 0, 0, 0, 0, 0,
            0, 0, 0, 0, 0, 0, 0, 0, 0, 0, 0, 0, 0, 0, 0, 0, 0, 0, 0, 0, 0, 0, 0, 0, 0, 0, 0, 0, 0, 0, 0, 0, 0, 0, 0, 0, 0, 0, 0, 0, 0, 0, 0, 0,
            0, 0, 0, 0, 0, 0, 0, 0, 0, 0, 0, 0, 0, 0, 0, 0, 0, 0, 0, 0, 0, 0, 0, 0, 0, 0, 0, 0, 0, 0, 0, 0, 0, 0, 0, 0, 0, 0, 0, 0, 0, 0, 0, 0,
            0, 0, 0, 0, 0, 0, 0, 0, 0, 0, 0, 0, 0, 0, 0, 0, 0, 0, 0, 0, 0, 0, 0, 0, 0, 0, 0, 0, 0, 0, 0, 0, 0, 0, 0, 0, 0, 0, 0, 0, 0, 0, 0, 0,
            0, 0, 0, 0, 0, 0, 0, 0, 0, 0, 0, 0, 0, 0, 0, 1577, 1578, 1579, 1580, 1581, 0, 0, 0, 0, 1577, 1578, 1579, 1580, 1581, 0, 0, 0, 0, 0, 0, 0, 0, 0, 0, 0, 0, 0, 0, 0,
            0, 0, 0, 0, 0, 0, 0, 0, 0, 0, 0, 0, 0, 0, 0, 0, 0, 0, 0, 0, 0, 0, 0, 0, 0, 0, 0, 0, 0, 0, 0, 0, 0, 0, 0, 0, 0, 0, 0, 0, 0, 0, 0, 0,
            0, 0, 0, 0, 0, 0, 0, 0, 0, 0, 0, 0, 0, 0, 0, 0, 0, 0, 0, 0, 0, 0, 0, 0, 0, 0, 0, 0, 0, 0, 0, 0, 0, 0, 0, 0, 0, 0, 0, 0, 0, 0, 0, 0,
            0, 0, 0, 0, 0, 0, 0, 0, 0, 0, 0, 0, 0, 0, 963, 0, 0, 0, 0, 0, 0, 0, 0, 963, 0, 0, 0, 0, 0, 0, 0, 0, 0, 0, 0, 0, 0, 0, 0, 0, 0, 0, 0, 0,
            0, 0, 0, 0, 0, 0, 0, 0, 0, 0, 0, 0, 0, 0, 0, 0, 0, 0, 0, 0, 0, 0, 0, 0, 0, 0, 0, 0, 0, 0, 0, 0, 0, 0, 0, 0, 0, 0, 0, 0, 0, 0, 0, 0,
            0, 0, 0, 0, 0, 0, 0, 0, 0, 0, 0, 0, 0, 0, 0, 0, 0, 0, 0, 0, 0, 0, 0, 0, 0, 0, 0, 0, 0, 0, 0, 0, 0, 0, 0, 0, 0, 0, 0, 0, 0, 0, 0, 0,
            0, 0, 0, 0, 0, 0, 0, 0, 0, 0, 0, 0, 0, 0, 0, 0, 0, 0, 0, 0, 0, 0, 3089, 3090, 3091, 3092, 3093, 3094, 3095, 3096, 0, 0, 0, 0, 0, 0, 0, 0, 0, 0, 0, 0, 0, 0,
            0, 0, 0, 0, 0, 0, 0, 0, 0, 0, 0, 0, 0, 0, 0, 0, 0, 0, 0, 0, 0, 0, 0, 0, 0, 0, 0, 0, 0, 0, 0, 0, 0, 0, 0, 0, 0, 0, 0, 0, 0, 0, 0, 0,
            0, 0, 0, 0, 0, 0, 0, 0, 0, 0, 0, 0, 0, 0, 0, 0, 0, 0, 0, 0, 0, 0, 0, 0, 0, 0, 0, 0, 0, 0, 0, 0, 0, 0, 0, 0, 0, 0, 0, 0, 0, 0, 0, 0,
            0, 0, 0, 0, 0, 0, 0, 0, 0, 0, 0, 0, 0, 0, 0, 0, 0, 0, 0, 0, 0, 0, 0, 0, 0, 0, 0, 0, 0, 0, 0, 0, 0, 0, 0, 0, 0, 0, 0, 0, 0, 0, 0, 0,
            0, 0, 0, 0, 0, 0, 0, 0, 0, 0, 0, 0, 0, 0, 0, 0, 0, 0, 0, 0, 0, 0, 0, 0, 0, 0, 0, 0, 0, 0, 0, 0, 0, 0, 0, 0, 0, 0, 0, 0, 0, 0, 0, 0,
            0, 0, 0, 0, 0, 0, 0, 0, 0, 0, 0, 0, 0, 0, 0, 0, 0, 0, 0, 0, 0, 0, 0, 0, 0, 0, 0, 0, 0, 0, 0, 0, 0, 0, 0, 0, 0, 0, 0, 0, 0, 0, 0, 0,
            0, 0, 0, 0, 0, 0, 0, 0, 0, 0, 0, 0, 0, 0, 0, 0, 0, 0, 0, 0, 0, 0, 0, 0, 0, 0, 0, 0, 0, 0, 0, 0, 0, 0, 0, 0, 0, 0, 0, 0, 0, 0, 0, 0,
            0, 0, 0, 0, 0, 0, 0, 0, 0, 0, 0, 0, 0, 0, 0, 0, 0, 0, 0, 0, 0, 0, 0, 0, 0, 0, 0, 0, 0, 0, 0, 0, 0, 0, 0, 0, 0, 0, 0, 0, 0, 0, 0, 0,
            0, 0, 0, 0, 0, 0, 0, 0, 0, 0, 0, 0, 0, 0, 0, 0, 0, 0, 0, 0, 0, 0, 0, 0, 0, 0, 0, 0, 0, 0, 0, 0, 0, 0, 0, 0, 0, 0, 0, 0, 0, 0, 0, 0,
            0, 0, 0, 0, 0, 0, 0, 0, 0, 0, 0, 0, 0, 0, 0, 0, 0, 0, 0, 0, 0, 0, 0, 0, 0, 0, 0, 0, 0, 0, 0, 0, 0, 0, 0, 0, 0, 0, 0, 0, 0, 0, 0, 0,
            0, 0, 0, 0, 0, 0, 0, 0, 0, 0, 0, 0, 0, 0, 0, 0, 0, 0, 0, 0, 0, 0, 0, 0, 0, 0, 0, 0, 0, 0, 0, 0, 0, 0, 0, 0, 0, 0, 0, 0, 0, 0, 0, 0,
            0, 0, 0, 0, 0, 0, 0, 0, 0, 0, 0, 0, 421, 422, 421, 422, 0, 0, 0, 0, 0, 0, 0, 0, 0, 0, 0, 0, 0, 0, 0, 0, 0, 0, 0, 0, 0, 0, 0, 0, 0, 0, 0, 0,
            0, 0, 0, 0, 0, 0, 0, 0, 0, 0, 0, 0, 0, 0, 0, 0, 0, 0, 0, 0, 0, 0, 0, 0, 0, 0, 0, 0, 0, 0, 0, 0, 0, 0, 0, 0, 0, 0, 0, 0, 0, 0, 0, 0,
            0, 0, 0, 0, 0, 0, 0, 0, 0, 0, 0, 0, 0, 0, 0, 0, 0, 0, 0, 0, 421, 422, 421, 422, 421, 422, 421, 422, 421, 422, 421, 422, 0, 0, 0, 0, 0, 0, 0, 0, 0, 0, 0, 0,
            0, 0, 0, 0, 0, 0, 0, 0, 0, 0, 0, 0, 0, 0, 0, 0, 0, 0, 0, 0, 0, 0, 0, 0, 0, 0, 0, 0, 0, 0, 0, 0, 0, 0, 0, 0, 0, 0, 0, 0, 0, 0, 0, 0,
            0, 0, 0, 0, 0, 0, 0, 0, 0, 0, 0, 0, 0, 0, 0, 0, 0, 0, 0, 0, 0, 0, 0, 0, 0, 0, 0, 0, 0, 0, 0, 0, 0, 0, 0, 0, 0, 0, 0, 0, 0, 0, 0, 0,
            0, 0, 0, 0, 0, 0, 0, 0, 0, 0, 0, 0, 0, 0, 0, 0, 0, 0, 0, 0, 0, 0, 0, 0, 0, 0, 0, 0, 0, 0, 0, 0, 0, 0, 0, 0, 0, 0, 0, 0, 0, 0, 0, 0,
            0, 0, 0, 0, 0, 0, 0, 0, 0, 0, 0, 0, 0, 0, 0, 0, 0, 0, 0, 0, 0, 0, 0, 0, 0, 0, 0, 0, 0, 0, 0, 0, 0, 0, 0, 0, 0, 0, 0, 0, 0, 0, 0, 0,
            0, 0, 0, 0, 0, 0, 0, 0, 0, 0, 0, 0, 0, 0, 0, 0, 0, 0, 0, 0, 0, 0, 0, 0, 0, 0, 0, 0, 0, 0, 0, 0, 0, 0, 0, 0, 0, 0, 0, 0, 0, 0, 0, 0,
            0, 0, 0, 0, 0, 0, 0, 0, 0, 0, 0, 0, 0, 0, 0, 0, 0, 0, 0, 0, 0, 0, 0, 0, 0, 0, 0, 0, 0, 0, 0, 0, 0, 0, 0, 0, 0, 0, 0, 0, 0, 0, 0, 0,
            0, 0, 0, 0, 0, 0, 0, 0, 0, 0, 0, 0, 0, 0, 0, 0, 0, 0, 0, 0, 0, 0, 0, 0, 0, 0, 0, 0, 0, 0, 0, 0, 0, 0, 0, 0, 0, 0, 0, 0, 0, 0, 0, 0,
            0, 0, 0, 0, 0, 0, 0, 0, 0, 0, 0, 0, 0, 0, 0, 0, 0, 0, 0, 0, 0, 0, 0, 0, 0, 0, 0, 0, 0, 0, 0, 0, 0, 0, 0, 0, 0, 0, 0, 0, 0, 0, 0, 0,
            0, 0, 0, 0, 0, 0, 0, 0, 0, 0, 0, 0, 0, 0, 0, 0, 0, 0, 0, 0, 0, 0, 0, 0, 0, 0, 0, 0, 0, 0, 0, 0, 0, 0, 0, 0, 0, 0, 0, 0, 0, 0, 0, 0,
            0, 0, 0, 0, 0, 0, 0, 0, 0, 0, 0, 0, 0, 0, 0, 0, 0, 0, 0, 0, 0, 0, 0, 0, 0, 0, 0, 0, 0, 0, 0, 0, 0, 0, 0, 0, 0, 0, 0, 0, 0, 0, 0, 0,
            0, 0, 0, 0, 0, 0, 0, 0, 0, 0, 0, 0, 0, 0, 0, 0, 0, 0, 0, 0, 0, 0, 0, 0, 0, 0, 0, 0, 0, 0, 0, 0, 0, 0, 0, 0, 0, 0, 0, 0, 0, 0, 0, 0,
            0, 0, 0, 0, 0, 0, 0, 0, 0, 0, 0, 0, 0, 0, 0, 0, 0, 0, 0, 0, 0, 0, 0, 0, 0, 0, 0, 0, 0, 0, 0, 0, 0, 0, 0, 0, 0, 0, 0, 0, 0, 0, 0, 0,
            0, 0, 0, 0, 0, 0, 0, 0, 0, 0, 0, 0, 0, 0, 0, 0, 0, 0, 0, 0, 0, 0, 0, 0, 0, 0, 0, 0, 0, 0, 0, 0, 0, 0, 0, 0, 0, 0, 0, 0, 0, 0, 0, 0,
            0, 0, 0, 0, 0, 0, 0, 0, 0, 0, 0, 0, 0, 0, 0, 0, 0, 0, 0, 0, 0, 0, 0, 0, 0, 0, 0, 0, 0, 0, 0, 0, 0, 0, 0, 0, 0, 0, 0, 0, 0, 0, 0, 0,
            0, 0, 0, 0, 0, 0, 0, 0, 0, 0, 0, 0, 0, 0, 0, 0, 0, 0, 0, 0, 0, 0, 0, 0, 0, 0, 0, 0, 0, 0, 0, 0, 0, 0, 0, 0, 0, 0, 0, 0, 0, 0, 0, 0,
            0, 0, 0, 0, 0, 0, 0, 0, 0, 0, 0, 0, 0, 0, 0, 0, 0, 0, 0, 0, 0, 0, 0, 0, 0, 0, 0, 0, 0, 0, 0, 0, 0, 0, 0, 0, 0, 0, 0, 0, 0, 0, 0, 0,
            0, 0, 0, 0, 0, 0, 0, 0, 0, 0, 0, 0, 0, 0, 0, 0, 0, 0, 0, 0, 0, 0, 0, 0, 0, 0, 0, 0, 0, 0, 0, 0, 0, 0, 0, 0, 0, 0, 0, 0, 0, 0, 0, 0],
         "height":44,
         "id":5,
         "name":"5",
         "opacity":1,
         "type":"tilelayer",
         "visible":false,
         "width":44,
         "x":0,
         "y":0
        }],
 "nextlayerid":6,
 "nextobjectid":1,
 "orientation":"orthogonal",
 "renderorder":"right-down",
 "tiledversion":"1.9.1",
 "tileheight":32,
 "tilesets":[
        {
         "firstgid":1,
         "source":"..\/..\/..\/..\/..\/..\/tiled\/pallet_town\/outside.tsx"
        }],
 "tilewidth":32,
 "type":"map",
 "version":"1.9",
 "width":44
}